Workbook

Sheet README
B2: SAILS Advisory
B3: The Sales Comp Plan Builder
B4: A working calculator for designing B2B SaaS sales compensation plans. Built for velocity motions.
B6: HOW TO USE THIS
B8: 1. Open the Comp Calculator tab. Edit ONLY the amber cells (base salary, base-to-variable ratio, quota multiple, accelerator multipliers).
B9: 2. Everything else computes automatically: variable comp, OTE, annual quota, commission rate, and accelerator rates.
B10: 3. The Attainment Scenarios tab shows what the rep takes home at 60% / 80% / 100% / 120% / 150% of quota, including accelerator math.
B11: 4. The Benchmarks tab gives healthy ranges by role (SMB AE, Mid-Market AE, Enterprise AE, BDR/SDR) so you can sanity-check your plan.
B12: 5. Sanity rules built in: base should be 40-60% of OTE, and quota should be 4-6x base. The calculator flags both ratios for you.
B14: THE 6 COMMON MISTAKES THIS HELPS YOU AVOID
B15: Base too high (attracts coasters) · No accelerators (reps coast after 100%) · Quota set too high (reps stop trying) · Paying on revenue you can't see · Changing the plan mid-year · Different plans for the same role.
B17: WANT A COMP PLAN DESIGNED FOR YOUR SPECIFIC MOTION?
... B21: © 2025 SAILS Advisory · sailsadvisory.com · matt@sailsadvisory.com

Sheet Comp Calculator
B2: Comp Calculator
B3: Edit the amber cells. Everything else computes automatically.
B5: INPUTS (edit these) | D5: Guidance
B6: Base salary ($) | C6: 80000 | D6: SMB AE: $60-80K · Mid-market: $80-110K · Enterprise: $110-150K
B7: Base-to-variable ratio (variable as % of base) | C7: 1 | D7: 1.0 = 1:1 (velocity standard). 0.7-0.8 for slower motions.
B8: Quota multiple (quota = base × this) | C8: 6 | D8: Healthy range: 4x to 6x base. Below 4x the role doesn't pay for itself.
B9: Accelerator: 100-125% band multiplier | C9: 1.5 | D9: Typical: 1.5x the base commission rate.
B10: Accelerator: 125%+ band multiplier | C10: 2 | D10: Typical: 2x. Raise to 2.5x if you want aggressive overachievement incentive.
B12: OUTPUTS (computed) | D12: Formula
B13: Variable comp at 100% ($) | C13: =C6*C7 | D13: Base × ratio
B14: OTE ($) | C14: =C6+C6*C7 | D14: Base + variable
B15: Annual quota ($ ARR) | C15: =C6*C8 | D15: Base × quota multiple
B16: Base as % of OTE | C16: =C6/(C6+C6*C7) | D16: Healthy: 40-60%
B17: Commission rate (up to 100%) | C17: =(C6*C7)/(C6*C8) | D17: Variable ÷ quota
B18: Commission rate (100-125% band) | C18: =((C6*C7)/(C6*C8))*C9 | D18: Base rate × accelerator 1
B19: Commission rate (125%+ band) | C19: =((C6*C7)/(C6*C8))*C10 | D19: Base rate × accelerator 2
B21: Sanity checks: Base % of OTE should land between 40% and 60%. Quota multiple should be 4x-6x. If either is out of range, adjust inputs before sending an offer.

Sheet Attainment Scenarios
B2: What the Rep Takes Home
B3: Earnings at each attainment level, using the inputs from the Comp Calculator tab. Accelerators applied per band.
B5: Attainment | C5: ARR closed | D5: Commission earned | E5: Base salary | F5: Total take-home
B6: 60% | C6: ='Comp Calculator'!C6*'Comp Calculator'!C8*0.6 | D6: ='Comp Calculator'!C6*'Comp Calculator'!C8*0.6*(('Comp Calculator'!C6*'Comp Calculator'!C7)/('Comp Calculator'!C6*'Comp Calculator'!C8)) | E6: ='Comp Calculator'!C6 | F6: =D6+E6
B7: 80% | C7: ='Comp Calculator'!C6*'Comp Calculator'!C8*0.8 | D7: ='Comp Calculator'!C6*'Comp Calculator'!C8*0.8*(('Comp Calculator'!C6*'Comp Calculator'!C7)/('Comp Calculator'!C6*'Comp Calculator'!C8)) | E7: ='Comp Calculator'!C6 | F7: =D7+E7
B8: 100% | C8: ='Comp Calculator'!C6*'Comp Calculator'!C8*1.0 | D8: ='Comp Calculator'!C6*'Comp Calculator'!C8*(('Comp Calculator'!C6*'Comp Calculator'!C7)/('Comp Calculator'!C6*'Comp Calculator'!C8)) | E8: ='Comp Calculator'!C6 | F8: =D8+E8
B9: 120% | C9: ='Comp Calculator'!C6*'Comp Calculator'!C8*1.2 | D9: ='Comp Calculator'!C6*'Comp Calculator'!C8*(('Comp Calculator'!C6*'Comp Calculator'!C7)/('Comp Calculator'!C6*'Comp Calculator'!C8))+'Comp Calculator'!C6*'Comp Calculator'!C8*0.2*(('Comp Calculator'!C6*'Comp Calculator'!C7)/('Comp Calculator'!C6*'Comp Calculator'!C8))*'Comp Calculator'!C9 | E9: ='Comp Calculator'!C6 | F9: =D9+E9
B10: 150% | C10: ='Comp Calculator'!C6*'Comp Calculator'!C8*1.5 | D10: ='Comp Calculator'!C6*'Comp Calculator'!C8*(('Comp Calculator'!C6*'Comp Calculator'!C7)/('Comp Calculator'!C6*'Comp Calculator'!C8))+'Comp Calculator'!C6*'Comp Calculator'!C8*0.25*(('Comp Calculator'!C6*'Comp Calculator'!C7)/('Comp Calculator'!C6*'Comp Calculator'!C8))*'Comp Calculator'!C9+'Comp Calculator'!C6*'Comp Calculator'!C8*0.25*(('Comp Calculator'!C6*'Comp Calculator'!C7)/('Comp Calculator'!C6*'Comp Calculator'!C8))*'Comp Calculator'!C10 | E10: ='Comp Calculator'!C6 | F10: =D10+E10
B12: Note: accelerator bands are 100-125% (multiplier 1) and 125%+ (multiplier 2), both set on the Comp Calculator tab. The 150% row shows the full effect: base band + accelerator band 1 + accelerator band 2.

Sheet Benchmarks
B2: Role Benchmarks · Velocity B2B SaaS
B3: Healthy ranges by role. Adjust ±15% for high cost-of-living markets, ±10% for rep experience.
B5: Role | C5: Base | D5: OTE | E5: Quota / target | F5: Notes
B6: BDR / SDR | C6: $50-70K | D6: $70-110K | E6: 8-15 meetings/mo | F6: Quota in meetings booked, not ARR. Variable pays per qualified meeting held.
B7: SMB AE (first hire) | C7: $60-80K | D7: $140-160K | E7: $400-480K ARR | F7: 1:1 base-to-variable. No draw after ramp. Accelerators above 100%.
B8: Mid-market AE | C8: $80-110K | D8: $180-220K | E8: $600-900K ARR | F8: Still 1:1 ratio. Larger deals justify higher quota multiple.
B9: Enterprise AE | C9: $110-150K | D9: $260-320K | E9: $1M-1.5M ARR | F9: 50/50 split typical. Longer cycles mean quarterly true-ups.
B10: Player-coach / Sales Mgr | C10: $100-130K | D10: $180-240K | E10: Team quota | F10: Variable tied to team attainment, not personal deals.
B13: Want a comp structure designed for your specific motion and stage?
B14: Book a discovery call: calendar.app.google/x2MYasUSFXEeow459
